{"cameraMode":{"drawMode":0,"name":"Shaded","section":"Shading Mode"},"sceneLighting":true,"audioPlay":false,"sceneViewState":{"m_AlwaysRefresh":false,"showFog":true,"showSkybox":true,"showFlares":true,"showImageEffects":true,"showParticleSystems":true,"showVisualEffectGraphs":true,"m_FxEnabled":true},"in2DMode":false,"pivot":{"x":48.264869689941409,"y":28.54134750366211,"z":-90.46598815917969},"rotation":{"x":-0.44717010855674746,"y":-0.1484687626361847,"z":-0.07557162642478943,"w":0.8788213133811951},"size":21.293502807617189,"orthographic":false}